metafed/__init__.py
metafed/algorithms/__init__.py
metafed/algorithms/fedavg.py
metafed/algorithms/fedprox.py
metafed/algorithms/scaffold.py
metafed/config/__init__.py
metafed/core/__init__.py
metafed/core/aggregation.py
metafed/core/client.py
metafed/core/server.py
metafed/data/__init__.py
metafed/data/loaders.py
metafed/green/__init__.py
metafed/green/carbon_tracking.py
metafed/models/__init__.py
metafed/models/simple_cnn.py
metafed/orchestration/__init__.py
metafed/orchestration/base.py
metafed/orchestration/random_orchestrator.py
metafed/privacy/__init__.py
metafed/privacy/differential_privacy.py
metafed/privacy/homomorphic_encryption.py
metafed/utils/__init__.py
metafed/utils/logging_config.py
metafed/utils/metrics.py
metafed_fl-1.0.0.dist-info/licenses/LICENSE
metafed_fl-1.0.0.dist-info/METADATA
metafed_fl-1.0.0.dist-info/WHEEL
metafed_fl-1.0.0.dist-info/entry_points.txt
metafed_fl-1.0.0.dist-info/top_level.txt
metafed_fl-1.0.0.dist-info/RECORD
