Metadata-Version: 2.4
Name: metafed-fl
Version: 1.0.0
Summary: Federated Learning for Metaverse Infrastructures with MARL, Privacy, and Sustainability
Home-page: https://github.com/afrilab/MetaFed-FL
Author: Muhammet Anil Yagiz, Zeynep Sude Cengiz, Polat Goktas
Author-email: Muhammet Anil Yagiz <anill.yagiz@gmail.com>, Zeynep Sude Cengiz <z.sude.cengiz@gmail.com>, Polat Goktas <polatgoktas@gmail.com>
License: MIT License
Project-URL: Homepage, https://github.com/afrilab/MetaFed-FL
Project-URL: Documentation, https://github.com/afrilab/MetaFed-FL#readme
Project-URL: Repository, https://github.com/afrilab/MetaFed-FL
Project-URL: Bug Tracker, https://github.com/afrilab/MetaFed-FL/issues
Keywords: federated learning,machine learning,distributed systems,privacy preserving,multi-agent reinforcement learning,carbon aware computing,sustainable AI,metaverse,PyTorch
Classifier: Development Status :: 4 - Beta
Classifier: Intended Audience :: Science/Research
Classifier: Intended Audience :: Developers
Classifier: License :: OSI Approved :: MIT License
Classifier: Operating System :: OS Independent
Classifier: Programming Language :: Python :: 3
Classifier: Programming Language :: Python :: 3.9
Classifier: Programming Language :: Python :: 3.10
Classifier: Programming Language :: Python :: 3.11
Classifier: Programming Language :: Python :: 3.12
Classifier: Topic :: Scientific/Engineering :: Artificial Intelligence
Classifier: Topic :: Software Development :: Libraries :: Python Modules
Classifier: Topic :: System :: Distributed Computing
Requires-Python: >=3.9
License-File: LICENSE
Requires-Dist: torch>=2.2.2
Requires-Dist: torchvision>=0.17.2
Requires-Dist: numpy>=1.26.4
Requires-Dist: pandas>=2.2.2
Requires-Dist: matplotlib>=3.9.2
Requires-Dist: timm>=1.0.8
Requires-Dist: pyyaml>=6.0
Requires-Dist: tqdm>=4.64.0
Requires-Dist: scikit-learn>=1.1.0
Requires-Dist: seaborn>=0.11.0
Provides-Extra: dev
Requires-Dist: pytest>=7.0.0; extra == "dev"
Requires-Dist: pytest-cov>=4.0.0; extra == "dev"
Requires-Dist: pytest-xdist>=3.0.0; extra == "dev"
Requires-Dist: black>=22.0.0; extra == "dev"
Requires-Dist: flake8>=5.0.0; extra == "dev"
Requires-Dist: isort>=5.10.0; extra == "dev"
Requires-Dist: mypy>=1.0.0; extra == "dev"
Requires-Dist: pre-commit>=2.20.0; extra == "dev"
Provides-Extra: docs
Requires-Dist: sphinx>=5.0.0; extra == "docs"
Requires-Dist: sphinx-rtd-theme>=1.0.0; extra == "docs"
Requires-Dist: sphinx-autodoc-typehints>=1.19.0; extra == "docs"
Requires-Dist: myst-parser>=0.18.0; extra == "docs"
Provides-Extra: experiments
Requires-Dist: jupyter>=1.0.0; extra == "experiments"
Requires-Dist: jupyterlab>=3.4.0; extra == "experiments"
Requires-Dist: ipywidgets>=8.0.0; extra == "experiments"
Requires-Dist: plotly>=5.10.0; extra == "experiments"
Provides-Extra: privacy
Requires-Dist: opacus>=1.4.0; extra == "privacy"
Provides-Extra: all
Requires-Dist: pytest>=7.0.0; extra == "all"
Requires-Dist: pytest-cov>=4.0.0; extra == "all"
Requires-Dist: pytest-xdist>=3.0.0; extra == "all"
Requires-Dist: black>=22.0.0; extra == "all"
Requires-Dist: flake8>=5.0.0; extra == "all"
Requires-Dist: isort>=5.10.0; extra == "all"
Requires-Dist: mypy>=1.0.0; extra == "all"
Requires-Dist: pre-commit>=2.20.0; extra == "all"
Requires-Dist: sphinx>=5.0.0; extra == "all"
Requires-Dist: sphinx-rtd-theme>=1.0.0; extra == "all"
Requires-Dist: sphinx-autodoc-typehints>=1.19.0; extra == "all"
Requires-Dist: myst-parser>=0.18.0; extra == "all"
Requires-Dist: jupyter>=1.0.0; extra == "all"
Requires-Dist: jupyterlab>=3.4.0; extra == "all"
Requires-Dist: ipywidgets>=8.0.0; extra == "all"
Requires-Dist: plotly>=5.10.0; extra == "all"
Requires-Dist: opacus>=1.4.0; extra == "all"
Dynamic: author
Dynamic: home-page
Dynamic: license-file
Dynamic: requires-python
